seqoria_agent/__init__.py
seqoria_agent/feature-implementation.md
seqoria_agent/client/__init__.py
seqoria_agent/client/client.py
seqoria_agent/client/core.py
seqoria_agent/client/parameters.py
seqoria_agent/client/simple_http_transport.py
seqoria_agent/client/cache/__init__.py
seqoria_agent/models/__init__.py
seqoria_agent/models/chunk.py
seqoria_agent/models/envelope.py
seqoria_agent/models/errors.py
seqoria_agent/providers/__init__.py
seqoria_agent/providers/anthropic_provider.py
seqoria_agent/providers/base_provider.py
seqoria_agent/providers/errors.py
seqoria_agent/providers/openai_provider.py
seqoria_agent/providers/schemas.py
seqoria_agent/server/__init__.py
seqoria_agent/server/formatters.py
seqoria_agent/server/fastxmcp/__init__.py
seqoria_agent/server/fastxmcp/app.py
seqoria_agent-0.1.0.dist-info/METADATA
seqoria_agent-0.1.0.dist-info/WHEEL
seqoria_agent-0.1.0.dist-info/licenses/LICENSE.txt
seqoria_agent-0.1.0.dist-info/RECORD
