Metadata-Version: 2.4
Name: seqoria_agent
Version: 0.1.0
Summary: Seqoria Agentic Assistant Framework for robust, tool-augmented AI applications.
Project-URL: Homepage, https://github.com/deandiasti/seqoria_agent
Project-URL: Documentation, https://deandiasti.github.io/seqoria_agent/
Project-URL: Repository, https://github.com/deandiasti/seqoria_agent
Author-email: Your Name <your@email.com>
License: MIT
License-File: LICENSE.txt
Classifier: License :: OSI Approved :: MIT License
Classifier: Operating System :: OS Independent
Classifier: Programming Language :: Python :: 3
Requires-Python: >=3.10
Requires-Dist: anthropic>=0.25.0
Requires-Dist: build>=1.2.2.post1
Requires-Dist: fastapi>=0.115.13
Requires-Dist: openai>=1.25.0
Requires-Dist: pydantic>=2.0
Requires-Dist: redis>=5.0.1
Requires-Dist: structlog>=24.1.0
Requires-Dist: twine>=6.1.0
Provides-Extra: dev
Requires-Dist: pytest-asyncio>=0.23.0; extra == 'dev'
Requires-Dist: pytest>=8.0.0; extra == 'dev'
Requires-Dist: ruff>=0.4.1; extra == 'dev'
Provides-Extra: docs
Requires-Dist: mkdocs-material>=9.5.18; extra == 'docs'
Requires-Dist: mkdocs>=1.6.0; extra == 'docs'
Requires-Dist: mkdocstrings[python]>=0.25.1; extra == 'docs'
Requires-Dist: pymdown-extensions>=10.8; extra == 'docs'
